graphical_anim/__init__.py
graphical_anim/examples.py
graphical_anim/props.py
graphical_anim/shapes.py
graphical_anim/video.py
graphical_anim-0.0.4.dist-info/LICENSE
graphical_anim-0.0.4.dist-info/METADATA
graphical_anim-0.0.4.dist-info/WHEEL
graphical_anim-0.0.4.dist-info/top_level.txt
graphical_anim-0.0.4.dist-info/RECORD
