Metadata-Version: 2.1
Name: graphical-anim
Version: 0.0.4
Summary: Python module to create graphical animations.
Home-page: https://github.com/HuangPatrick16777216/graphical_anim
Author: Patrick Huang and Arjun Sahlot
Author-email: huangpatrick16777216@gmail.com
License: UNKNOWN
Platform: UNKNOWN
Classifier: Programming Language :: Python :: 3
Classifier: License :: OSI Approved :: GNU General Public License v2 or later (GPLv2+)
Classifier: Operating System :: OS Independent
Requires-Dist: pygame
Requires-Dist: numpy
Requires-Dist: opencv-python
Requires-Dist: pillow
